README.rst
setup.py
django_safety.egg-info/PKG-INFO
django_safety.egg-info/SOURCES.txt
django_safety.egg-info/dependency_links.txt
django_safety.egg-info/not-zip-safe
django_safety.egg-info/requires.txt
django_safety.egg-info/top_level.txt
example/__init__.py
example/models.py
example/settings.py
example/urls.py
safety/__init__.py
safety/admin.py
safety/app_settings.py
safety/apps.py
safety/compat.py
safety/decorators.py
safety/forms.py
safety/managers.py
safety/middleware.py
safety/mixins.py
safety/models.py
safety/resolvers.py
safety/urls.py
safety/utils.py
safety/views.py
safety/management/__init__.py
safety/management/commands/__init__.py
safety/management/commands/clean_safety_sessions.py
safety/tests/__init__.py
safety/tests/base.py
safety/tests/models.py
safety/tests/settings.py
safety/tests/test_models.py
safety/tests/test_views.py
safety/tests/urls.py