Metadata-Version: 1.1
Name: django-safety
Version: 0.1.0
Summary: Generic Django application for safer user accounts
Home-page: http://github.com/ulule/django-safety
Author: Gilles Fabio
Author-email: gilles.fabio@gmail.com
License: UNKNOWN
Platform: UNKNOWN
Classifier: Environment :: Web Environment
Classifier: Framework :: Django
Classifier: Intended Audience :: Developers
Classifier: License :: OSI Approved :: MIT License
Classifier: Operating System :: OS Independent
Classifier: Programming Language :: Python
Classifier: Programming Language :: Python :: 2.7
Classifier: Programming Language :: Python :: 3
Classifier: Programming Language :: Python :: 3.4
Classifier: Programming Language :: Python :: 3.5
